forte.allennlp-0.0.3-py3.7-nspkg.pth
fortex/allennlp/__init__.py
fortex/allennlp/allennlp_processors.py
fortex/allennlp/utils_processor.py
forte.allennlp-0.0.3.dist-info/METADATA
forte.allennlp-0.0.3.dist-info/WHEEL
forte.allennlp-0.0.3.dist-info/namespace_packages.txt
forte.allennlp-0.0.3.dist-info/top_level.txt
forte.allennlp-0.0.3.dist-info/RECORD
